{
  "books": {
    "B1": {
      "id": "B1",
      "title": "Bhagat Singh",
      "author": "Rohit",
      "genre": "History",
      "available": false
    },
    "B2": {
      "id": "B2",
      "title": "Modern India",
      "author": "Saikat Mehrul",
      "genre": "Philosophy",
      "available": false
    },
    "B3": {
      "id": "B3",
      "title": "Arranged Marriage",
      "author": "Chetan Bhagat",
      "genre": "fantasy",
      "available": true
    }
  },
  "members": {
    "M1": {
      "id": "M1",
      "name": "Kousthuban",
      "age": 50,
      "contact": "Kousthub@gmail.com",
      "borrowed_books": []
    },
    "M2": {
      "id": "M2",
      "name": "Swapna",
      "age": 22,
      "contact": "Swapna@yahoo.com",
      "borrowed_books": [
        "B2",
        "B1"
      ]
    }
  },
  "borrow_log": [
    {
      "timestamp": "2026-05-20 21:11:31",
      "member_id": "M1",
      "book_id": "B1",
      "action": "issued"
    },
    {
      "timestamp": "2026-05-20 21:11:31",
      "member_id": "M2",
      "book_id": "B2",
      "action": "issued"
    },
    {
      "timestamp": "2026-05-20 21:11:31",
      "member_id": "M1",
      "book_id": "B1",
      "action": "returned"
    },
    {
      "timestamp": "2026-05-20 21:11:31",
      "member_id": "M2",
      "book_id": "B1",
      "action": "issued"
    }
  ],
  "genre_popularity": {
    "fantasy": 2,
    "science": 1
  }
}